xh_dict_utils/__init__.py
xh_dict_utils/__main__.py
xh_dict_utils/app.py
xh_dict_utils/dict_utils.py
xh_dict_utils/test_dict_utils.py
xh_dict_utils/command/LoadFile.py
xh_dict_utils/command/LoadPipe.py
xh_dict_utils/command/Output.py
xh_dict_utils/command/Query.py
xh_dict_utils/command/RemoveNode.py
xh_dict_utils/command/ToArray.py
xh_dict_utils/command/UpsertNode.py
xh_dict_utils/supports/Logger.py
xh_dict_utils/supports/SupportedFormat.py
xh_dict_utils-0.0.31.dist-info/LICENSE.txt
xh_dict_utils-0.0.31.dist-info/METADATA
xh_dict_utils-0.0.31.dist-info/WHEEL
xh_dict_utils-0.0.31.dist-info/top_level.txt
xh_dict_utils-0.0.31.dist-info/RECORD
